[
  {
    "ns": 0,
    "pageid": 1283211,
    "title": "Archimedean solids"
  },
  {
    "ns": 0,
    "pageid": 4418950,
    "title": "Archimedean dual"
  },
  {
    "ns": 0,
    "pageid": 4862481,
    "title": "Archimedean bodies"
  },
  {
    "ns": 0,
    "pageid": 4862485,
    "title": "Archimedean body"
  },
  {
    "ns": 0,
    "pageid": 8857327,
    "title": "Archimedean Solid"
  },
  {
    "ns": 0,
    "pageid": 16104983,
    "title": "Archimedean Solids"
  },
  {
    "ns": 0,
    "pageid": 41388527,
    "title": "Archimedean polyhedron"
  }
]