[
  {
    "ns": 0,
    "pageid": 161262,
    "title": "Circumcircle"
  },
  {
    "ns": 0,
    "pageid": 204267,
    "title": "Circumcenter"
  },
  {
    "ns": 0,
    "pageid": 221320,
    "title": "Cyclic polygon"
  },
  {
    "ns": 0,
    "pageid": 3189438,
    "title": "Circumradius"
  },
  {
    "ns": 0,
    "pageid": 3557198,
    "title": "Circumscribe"
  },
  {
    "ns": 0,
    "pageid": 4576871,
    "title": "Circumscribed"
  },
  {
    "ns": 0,
    "pageid": 4850965,
    "title": "Circumcentre"
  },
  {
    "ns": 0,
    "pageid": 5041687,
    "title": "Circuminscribed"
  },
  {
    "ns": 0,
    "pageid": 15806898,
    "title": "Triangle Circumscribing"
  },
  {
    "ns": 0,
    "pageid": 15806900,
    "title": "Triangle circumscribing"
  },
  {
    "ns": 0,
    "pageid": 17433781,
    "title": "Circumscribes"
  },
  {
    "ns": 0,
    "pageid": 17433794,
    "title": "Circumscribing"
  },
  {
    "ns": 0,
    "pageid": 19415641,
    "title": "Circum-circle"
  },
  {
    "ns": 0,
    "pageid": 34129839,
    "title": "Circumcircular"
  },
  {
    "ns": 0,
    "pageid": 35435632,
    "title": "Concyclic polygon"
  },
  {
    "ns": 0,
    "pageid": 35916147,
    "title": "Alternate segment theorem"
  },
  {
    "ns": 0,
    "pageid": 42792971,
    "title": "Polygon circumscribing constant"
  }
]