{
  "comment": "/* See also */ if criticising atheism is a link then criticising religion ought also to be one in order to be neutral",
  "timestamp": "2007-08-28T16:56:35Z",
  "revid": 154203069,
  "user": "Richard holt",
  "parentid": 154202146,
  "diff": {
    "to": 154203069,
    "*": "<tr>\n  <td colspan=\"2\" class=\"diff-lineno\">Line 93:</td>\n  <td colspan=\"2\" class=\"diff-lineno\">Line 93:</td>\n</tr>\n<tr>\n  <td class=\"diff-marker\">&#160;</td>\n  <td class=\"diff-context\"><div>* [[Moral particularism]]</div></td>\n  <td class=\"diff-marker\">&#160;</td>\n  <td class=\"diff-context\"><div>* [[Moral particularism]]</div></td>\n</tr>\n<tr>\n  <td class=\"diff-marker\">&#160;</td>\n  <td class=\"diff-context\"><div>* [[Guilt]]</div></td>\n  <td class=\"diff-marker\">&#160;</td>\n  <td class=\"diff-context\"><div>* [[Guilt]]</div></td>\n</tr>\n<tr>\n  <td class=\"diff-marker\">−</td>\n  <td class=\"diff-deletedline\"><div>* [[Criticism of <del class=\"diffchange diffchange-inline\">atheism</del>]]</div></td>\n  <td class=\"diff-marker\">+</td>\n  <td class=\"diff-addedline\"><div>* [[Criticism of <ins class=\"diffchange diffchange-inline\">Atheism</ins>]]</div></td>\n</tr>\n<tr>\n  <td class=\"diff-marker\">−</td>\n  <td class=\"diff-deletedline\"><div>* [[Criticism of <del class=\"diffchange diffchange-inline\">atheism#Atheism and morality|Atheism and morality</del>]]</div></td>\n  <td class=\"diff-marker\">+</td>\n  <td class=\"diff-addedline\"><div>* [[Criticism of <ins class=\"diffchange diffchange-inline\">Religion</ins>]]</div></td>\n</tr>\n<tr>\n  <td class=\"diff-marker\">&#160;</td>\n  <td class=\"diff-context\"><div>* [[Conscience]]</div></td>\n  <td class=\"diff-marker\">&#160;</td>\n  <td class=\"diff-context\"><div>* [[Conscience]]</div></td>\n</tr>\n<tr>\n  <td class=\"diff-marker\">&#160;</td>\n  <td class=\"diff-context\"><div>* [[Kohlberg's stages of moral development]]</div></td>\n  <td class=\"diff-marker\">&#160;</td>\n  <td class=\"diff-context\"><div>* [[Kohlberg's stages of moral development]]</div></td>\n</tr>\n\n<!-- diff cache key enwiki:diff:version:1.11a:oldid:154202146:newid:154203069 -->\n",
    "from": 154202146
  }
}