{
  "comment": "/* External links */",
  "timestamp": "2006-03-20T13:56:51Z",
  "revid": 44661071,
  "anon": "",
  "user": "134.67.6.24",
  "parentid": 44660929,
  "diff": {
    "to": 44661071,
    "*": "<tr>\n  <td colspan=\"2\" class=\"diff-lineno\">Line 94:</td>\n  <td colspan=\"2\" class=\"diff-lineno\">Line 94:</td>\n</tr>\n<tr>\n  <td class=\"diff-marker\">&#160;</td>\n  <td class=\"diff-context\"><div>* [http://www.examinethetruth.com/page_morale_01.htm Christian and Muslim debates on Morality]</div></td>\n  <td class=\"diff-marker\">&#160;</td>\n  <td class=\"diff-context\"><div>* [http://www.examinethetruth.com/page_morale_01.htm Christian and Muslim debates on Morality]</div></td>\n</tr>\n<tr>\n  <td class=\"diff-marker\">&#160;</td>\n  <td class=\"diff-context\"><div>* [http://www.chabad.org/search/keyword.asp?kid=1222 Morality and Judaism] chabad.org</div></td>\n  <td class=\"diff-marker\">&#160;</td>\n  <td class=\"diff-context\"><div>* [http://www.chabad.org/search/keyword.asp?kid=1222 Morality and Judaism] chabad.org</div></td>\n</tr>\n<tr>\n  <td class=\"diff-marker\">−</td>\n  <td class=\"diff-deletedline\"><div></div></td>\n  <td class=\"diff-marker\">+</td>\n  <td class=\"diff-addedline\"><div><ins class=\"diffchange diffchange-inline\">* [http://www.geeta-kavita.com/article.asp?article=biology_morals_dharma An article that focuses on the Biological basis of morals is available at Geeta-kavita.com]</ins></div></td>\n</tr>\n<tr>\n  <td class=\"diff-marker\">&#160;</td>\n  <td class=\"diff-context\"></td>\n  <td class=\"diff-marker\">&#160;</td>\n  <td class=\"diff-context\"></td>\n</tr>\n<tr>\n  <td class=\"diff-marker\">&#160;</td>\n  <td class=\"diff-context\"></td>\n  <td class=\"diff-marker\">&#160;</td>\n  <td class=\"diff-context\"></td>\n</tr>\n\n<!-- diff cache key enwiki:diff:version:1.11a:oldid:44660929:newid:44661071 -->\n",
    "from": 44660929
  }
}