{
  "comment": "Reverted edits by [[Special:Contributions/65.7.82.245|65.7.82.245]] to last version by Jfdwolff",
  "timestamp": "2005-09-05T12:02:16Z",
  "revid": 22616600,
  "user": "Jfdwolff",
  "parentid": 22612819,
  "diff": {
    "to": 22616600,
    "*": "<tr>\n  <td colspan=\"2\" class=\"diff-lineno\">Line 248:</td>\n  <td colspan=\"2\" class=\"diff-lineno\">Line 248:</td>\n</tr>\n<tr>\n  <td class=\"diff-marker\">&#160;</td>\n  <td class=\"diff-context\"><div>* [http://buddhism.kalachakranet.org/immeasurables.html A Buddhist View on Love and Compassion]</div></td>\n  <td class=\"diff-marker\">&#160;</td>\n  <td class=\"diff-context\"><div>* [http://buddhism.kalachakranet.org/immeasurables.html A Buddhist View on Love and Compassion]</div></td>\n</tr>\n<tr>\n  <td class=\"diff-marker\">&#160;</td>\n  <td class=\"diff-context\"><div>* [http://plato.stanford.edu/entries/love/ Stanford Encyclopedia of Philosophy entry]</div></td>\n  <td class=\"diff-marker\">&#160;</td>\n  <td class=\"diff-context\"><div>* [http://plato.stanford.edu/entries/love/ Stanford Encyclopedia of Philosophy entry]</div></td>\n</tr>\n<tr>\n  <td class=\"diff-marker\">−</td>\n  <td class=\"diff-deletedline\"><div>* [http://www.johnlovesraquel.com John Loves Raquel] - One man's quest to find his missing fiancee.</div></td>\n  <td colspan=\"2\" class=\"diff-empty\">&#160;</td>\n</tr>\n<tr>\n  <td class=\"diff-marker\">&#160;</td>\n  <td class=\"diff-context\"></td>\n  <td class=\"diff-marker\">&#160;</td>\n  <td class=\"diff-context\"></td>\n</tr>\n<tr>\n  <td class=\"diff-marker\">&#160;</td>\n  <td class=\"diff-context\"><div>[[Category:Love]]</div></td>\n  <td class=\"diff-marker\">&#160;</td>\n  <td class=\"diff-context\"><div>[[Category:Love]]</div></td>\n</tr>\n\n<!-- diff cache key enwiki:diff:version:1.11a:oldid:22612819:newid:22616600 -->\n",
    "from": 22612819
  },
  "minor": ""
}