{
  "comment": "",
  "timestamp": "2004-03-27T00:00:43Z",
  "revid": 2933289,
  "anon": "",
  "user": "66.134.197.14",
  "parentid": 2933248,
  "diff": {
    "to": 2933289,
    "*": "<tr>\n  <td colspan=\"2\" class=\"diff-lineno\">Line 47:</td>\n  <td colspan=\"2\" class=\"diff-lineno\">Line 47:</td>\n</tr>\n<tr>\n  <td class=\"diff-marker\">&#160;</td>\n  <td class=\"diff-context\"></td>\n  <td class=\"diff-marker\">&#160;</td>\n  <td class=\"diff-context\"></td>\n</tr>\n<tr>\n  <td class=\"diff-marker\">&#160;</td>\n  <td class=\"diff-context\"><div>==List of \"I love you\" in all languages==</div></td>\n  <td class=\"diff-marker\">&#160;</td>\n  <td class=\"diff-context\"><div>==List of \"I love you\" in all languages==</div></td>\n</tr>\n<tr>\n  <td class=\"diff-marker\">−</td>\n  <td class=\"diff-deletedline\"><div>*English: I love you</div></td>\n  <td class=\"diff-marker\">+</td>\n  <td class=\"diff-addedline\"><div>*<ins class=\"diffchange diffchange-inline\">[[</ins>English<ins class=\"diffchange diffchange-inline\">]]</ins>: I love you</div></td>\n</tr>\n<tr>\n  <td class=\"diff-marker\">−</td>\n  <td class=\"diff-deletedline\"><div>*French: Je t'aime</div></td>\n  <td class=\"diff-marker\">+</td>\n  <td class=\"diff-addedline\"><div>*<ins class=\"diffchange diffchange-inline\">[[</ins>French<ins class=\"diffchange diffchange-inline\">]]</ins>: Je t'aime</div></td>\n</tr>\n<tr>\n  <td class=\"diff-marker\">−</td>\n  <td class=\"diff-deletedline\"><div>*German: Ich liebe dich</div></td>\n  <td class=\"diff-marker\">+</td>\n  <td class=\"diff-addedline\"><div>*<ins class=\"diffchange diffchange-inline\">[[</ins>German<ins class=\"diffchange diffchange-inline\">]]</ins>: Ich liebe dich</div></td>\n</tr>\n<tr>\n  <td class=\"diff-marker\">−</td>\n  <td class=\"diff-deletedline\"><div>*Japanese: Kimi o ai shiteru </div></td>\n  <td class=\"diff-marker\">+</td>\n  <td class=\"diff-addedline\"><div>*<ins class=\"diffchange diffchange-inline\">[[</ins>Japanese<ins class=\"diffchange diffchange-inline\">]]</ins>: Kimi o ai shiteru </div></td>\n</tr>\n<tr>\n  <td class=\"diff-marker\">−</td>\n  <td class=\"diff-deletedline\"><div>*Chinese: Wo3 ai4 ni2</div></td>\n  <td class=\"diff-marker\">+</td>\n  <td class=\"diff-addedline\"><div>*<ins class=\"diffchange diffchange-inline\">[[</ins>Chinese<ins class=\"diffchange diffchange-inline\">]]</ins>: Wo3 ai4 ni2</div></td>\n</tr>\n<tr>\n  <td class=\"diff-marker\">−</td>\n  <td class=\"diff-deletedline\"><div>*Hebrew: Ani ohev otach     </div></td>\n  <td class=\"diff-marker\">+</td>\n  <td class=\"diff-addedline\"><div>*<ins class=\"diffchange diffchange-inline\">[[</ins>Hebrew<ins class=\"diffchange diffchange-inline\">]]</ins>: Ani ohev otach     </div></td>\n</tr>\n<tr>\n  <td class=\"diff-marker\">−</td>\n  <td class=\"diff-deletedline\"><div>*Arabic: Ana Ba-heb-bak </div></td>\n  <td class=\"diff-marker\">+</td>\n  <td class=\"diff-addedline\"><div>*<ins class=\"diffchange diffchange-inline\">[[</ins>Arabic<ins class=\"diffchange diffchange-inline\">]]</ins>: Ana Ba-heb-bak </div></td>\n</tr>\n<tr>\n  <td class=\"diff-marker\">−</td>\n  <td class=\"diff-deletedline\"><div>*Czech: Miluji te</div></td>\n  <td class=\"diff-marker\">+</td>\n  <td class=\"diff-addedline\"><div>*<ins class=\"diffchange diffchange-inline\">[[</ins>Czech<ins class=\"diffchange diffchange-inline\">]]</ins>: Miluji te</div></td>\n</tr>\n<tr>\n  <td class=\"diff-marker\">&#160;</td>\n  <td class=\"diff-context\"></td>\n  <td class=\"diff-marker\">&#160;</td>\n  <td class=\"diff-context\"></td>\n</tr>\n<tr>\n  <td class=\"diff-marker\">&#160;</td>\n  <td class=\"diff-context\"><div>== Quotes about love ==</div></td>\n  <td class=\"diff-marker\">&#160;</td>\n  <td class=\"diff-context\"><div>== Quotes about love ==</div></td>\n</tr>\n\n<!-- diff cache key enwiki:diff:version:1.11a:oldid:2933248:newid:2933289 -->\n",
    "from": 2933248
  }
}