{
  "comment": "/* Sternberg's Triangular Theory of Love */ reformating the table. please objcet",
  "timestamp": "2005-12-18T00:07:35Z",
  "revid": 31787793,
  "user": "Kirils",
  "parentid": 31614344,
  "diff": {
    "to": 31787793,
    "*": "<tr>\n  <td colspan=\"2\" class=\"diff-lineno\">Line 32:</td>\n  <td colspan=\"2\" class=\"diff-lineno\">Line 32:</td>\n</tr>\n<tr>\n  <td class=\"diff-marker\">&#160;</td>\n  <td class=\"diff-context\"><div>{| border=1 cellpadding=3 cellspacing=0</div></td>\n  <td class=\"diff-marker\">&#160;</td>\n  <td class=\"diff-context\"><div>{| border=1 cellpadding=3 cellspacing=0</div></td>\n</tr>\n<tr>\n  <td class=\"diff-marker\">&#160;</td>\n  <td class=\"diff-context\"><div>|+'''Combinations of intimacy, passion, and commitment'''</div></td>\n  <td class=\"diff-marker\">&#160;</td>\n  <td class=\"diff-context\"><div>|+'''Combinations of intimacy, passion, and commitment'''</div></td>\n</tr>\n<tr>\n  <td colspan=\"2\" class=\"diff-empty\">&#160;</td>\n  <td class=\"diff-marker\">+</td>\n  <td class=\"diff-addedline\"><div>|-</div></td>\n</tr>\n<tr>\n  <td colspan=\"2\" class=\"diff-empty\">&#160;</td>\n  <td class=\"diff-marker\">+</td>\n  <td class=\"diff-addedline\"><div>|&amp;nbsp;</div></td>\n</tr>\n<tr>\n  <td colspan=\"2\" class=\"diff-empty\">&#160;</td>\n  <td class=\"diff-marker\">+</td>\n  <td class=\"diff-addedline\"><div>|'''intimacy'''</div></td>\n</tr>\n<tr>\n  <td colspan=\"2\" class=\"diff-empty\">&#160;</td>\n  <td class=\"diff-marker\">+</td>\n  <td class=\"diff-addedline\"><div>|'''passion'''</div></td>\n</tr>\n<tr>\n  <td colspan=\"2\" class=\"diff-empty\">&#160;</td>\n  <td class=\"diff-marker\">+</td>\n  <td class=\"diff-addedline\"><div>|'''commitment'''</div></td>\n</tr>\n<tr>\n  <td class=\"diff-marker\">&#160;</td>\n  <td class=\"diff-context\"><div>|-</div></td>\n  <td class=\"diff-marker\">&#160;</td>\n  <td class=\"diff-context\"><div>|-</div></td>\n</tr>\n<tr>\n  <td class=\"diff-marker\">&#160;</td>\n  <td class=\"diff-context\"><div>|'''[[Like#As a verb|Liking]]''' or '''[[friendship]]'''</div></td>\n  <td class=\"diff-marker\">&#160;</td>\n  <td class=\"diff-context\"><div>|'''[[Like#As a verb|Liking]]''' or '''[[friendship]]'''</div></td>\n</tr>\n<tr>\n  <td class=\"diff-marker\">−</td>\n  <td class=\"diff-deletedline\"><div>|<del class=\"diffchange diffchange-inline\">intimacy</del></div></td>\n  <td class=\"diff-marker\">+</td>\n  <td class=\"diff-addedline\"><div>|<ins class=\"diffchange diffchange-inline\">&lt;center&gt;x&lt;/center&gt;</ins></div></td>\n</tr>\n<tr>\n  <td class=\"diff-marker\">&#160;</td>\n  <td class=\"diff-context\"><div>|&amp;nbsp;</div></td>\n  <td class=\"diff-marker\">&#160;</td>\n  <td class=\"diff-context\"><div>|&amp;nbsp;</div></td>\n</tr>\n<tr>\n  <td class=\"diff-marker\">&#160;</td>\n  <td class=\"diff-context\"><div>|&amp;nbsp;</div></td>\n  <td class=\"diff-marker\">&#160;</td>\n  <td class=\"diff-context\"><div>|&amp;nbsp;</div></td>\n</tr>\n<tr>\n  <td colspan=\"2\" class=\"diff-lineno\">Line 40:</td>\n  <td colspan=\"2\" class=\"diff-lineno\">Line 45:</td>\n</tr>\n<tr>\n  <td class=\"diff-marker\">&#160;</td>\n  <td class=\"diff-context\"><div>|[[Limerence|'''Infatuation''' or '''limerence''']]</div></td>\n  <td class=\"diff-marker\">&#160;</td>\n  <td class=\"diff-context\"><div>|[[Limerence|'''Infatuation''' or '''limerence''']]</div></td>\n</tr>\n<tr>\n  <td class=\"diff-marker\">&#160;</td>\n  <td class=\"diff-context\"><div>|&amp;nbsp;</div></td>\n  <td class=\"diff-marker\">&#160;</td>\n  <td class=\"diff-context\"><div>|&amp;nbsp;</div></td>\n</tr>\n<tr>\n  <td class=\"diff-marker\">−</td>\n  <td class=\"diff-deletedline\"><div>|<del class=\"diffchange diffchange-inline\">passion</del></div></td>\n  <td class=\"diff-marker\">+</td>\n  <td class=\"diff-addedline\"><div>|<ins class=\"diffchange diffchange-inline\">&lt;center&gt;x&lt;/center&gt;</ins></div></td>\n</tr>\n<tr>\n  <td class=\"diff-marker\">&#160;</td>\n  <td class=\"diff-context\"><div>|&amp;nbsp;</div></td>\n  <td class=\"diff-marker\">&#160;</td>\n  <td class=\"diff-context\"><div>|&amp;nbsp;</div></td>\n</tr>\n<tr>\n  <td class=\"diff-marker\">&#160;</td>\n  <td class=\"diff-context\"><div>|-</div></td>\n  <td class=\"diff-marker\">&#160;</td>\n  <td class=\"diff-context\"><div>|-</div></td>\n</tr>\n<tr>\n  <td colspan=\"2\" class=\"diff-lineno\">Line 46:</td>\n  <td colspan=\"2\" class=\"diff-lineno\">Line 51:</td>\n</tr>\n<tr>\n  <td class=\"diff-marker\">&#160;</td>\n  <td class=\"diff-context\"><div>|&amp;nbsp;</div></td>\n  <td class=\"diff-marker\">&#160;</td>\n  <td class=\"diff-context\"><div>|&amp;nbsp;</div></td>\n</tr>\n<tr>\n  <td class=\"diff-marker\">&#160;</td>\n  <td class=\"diff-context\"><div>|&amp;nbsp;</div></td>\n  <td class=\"diff-marker\">&#160;</td>\n  <td class=\"diff-context\"><div>|&amp;nbsp;</div></td>\n</tr>\n<tr>\n  <td class=\"diff-marker\">−</td>\n  <td class=\"diff-deletedline\"><div>|<del class=\"diffchange diffchange-inline\">commitment</del></div></td>\n  <td class=\"diff-marker\">+</td>\n  <td class=\"diff-addedline\"><div>|<ins class=\"diffchange diffchange-inline\">&lt;center&gt;x&lt;/center&gt;</ins></div></td>\n</tr>\n<tr>\n  <td class=\"diff-marker\">&#160;</td>\n  <td class=\"diff-context\"><div>|-</div></td>\n  <td class=\"diff-marker\">&#160;</td>\n  <td class=\"diff-context\"><div>|-</div></td>\n</tr>\n<tr>\n  <td class=\"diff-marker\">&#160;</td>\n  <td class=\"diff-context\"><div>|'''[[Romantic love]]'''</div></td>\n  <td class=\"diff-marker\">&#160;</td>\n  <td class=\"diff-context\"><div>|'''[[Romantic love]]'''</div></td>\n</tr>\n<tr>\n  <td class=\"diff-marker\">−</td>\n  <td class=\"diff-deletedline\"><div>|<del class=\"diffchange diffchange-inline\">intimacy</del></div></td>\n  <td class=\"diff-marker\">+</td>\n  <td class=\"diff-addedline\"><div>|<ins class=\"diffchange diffchange-inline\">&lt;center&gt;x&lt;/center&gt;</ins></div></td>\n</tr>\n<tr>\n  <td class=\"diff-marker\">−</td>\n  <td class=\"diff-deletedline\"><div>|<del class=\"diffchange diffchange-inline\">passion</del></div></td>\n  <td class=\"diff-marker\">+</td>\n  <td class=\"diff-addedline\"><div>|<ins class=\"diffchange diffchange-inline\">&lt;center&gt;x&lt;/center&gt;</ins></div></td>\n</tr>\n<tr>\n  <td class=\"diff-marker\">&#160;</td>\n  <td class=\"diff-context\"><div>|&amp;nbsp;</div></td>\n  <td class=\"diff-marker\">&#160;</td>\n  <td class=\"diff-context\"><div>|&amp;nbsp;</div></td>\n</tr>\n<tr>\n  <td class=\"diff-marker\">&#160;</td>\n  <td class=\"diff-context\"><div>|-</div></td>\n  <td class=\"diff-marker\">&#160;</td>\n  <td class=\"diff-context\"><div>|-</div></td>\n</tr>\n<tr>\n  <td class=\"diff-marker\">&#160;</td>\n  <td class=\"diff-context\"><div>|'''Companionate love'''</div></td>\n  <td class=\"diff-marker\">&#160;</td>\n  <td class=\"diff-context\"><div>|'''Companionate love'''</div></td>\n</tr>\n<tr>\n  <td class=\"diff-marker\">−</td>\n  <td class=\"diff-deletedline\"><div>|<del class=\"diffchange diffchange-inline\">intimacy</del></div></td>\n  <td class=\"diff-marker\">+</td>\n  <td class=\"diff-addedline\"><div>|<ins class=\"diffchange diffchange-inline\">&lt;center&gt;x&lt;/center&gt;</ins></div></td>\n</tr>\n<tr>\n  <td class=\"diff-marker\">&#160;</td>\n  <td class=\"diff-context\"><div>|&amp;nbsp;</div></td>\n  <td class=\"diff-marker\">&#160;</td>\n  <td class=\"diff-context\"><div>|&amp;nbsp;</div></td>\n</tr>\n<tr>\n  <td class=\"diff-marker\">−</td>\n  <td class=\"diff-deletedline\"><div>|<del class=\"diffchange diffchange-inline\">commitment</del></div></td>\n  <td class=\"diff-marker\">+</td>\n  <td class=\"diff-addedline\"><div>|<ins class=\"diffchange diffchange-inline\">&lt;center&gt;x&lt;/center&gt;</ins></div></td>\n</tr>\n<tr>\n  <td class=\"diff-marker\">&#160;</td>\n  <td class=\"diff-context\"><div>|-</div></td>\n  <td class=\"diff-marker\">&#160;</td>\n  <td class=\"diff-context\"><div>|-</div></td>\n</tr>\n<tr>\n  <td class=\"diff-marker\">&#160;</td>\n  <td class=\"diff-context\"><div>|'''Fatuous love'''</div></td>\n  <td class=\"diff-marker\">&#160;</td>\n  <td class=\"diff-context\"><div>|'''Fatuous love'''</div></td>\n</tr>\n<tr>\n  <td class=\"diff-marker\">&#160;</td>\n  <td class=\"diff-context\"><div>|&amp;nbsp;</div></td>\n  <td class=\"diff-marker\">&#160;</td>\n  <td class=\"diff-context\"><div>|&amp;nbsp;</div></td>\n</tr>\n<tr>\n  <td class=\"diff-marker\">−</td>\n  <td class=\"diff-deletedline\"><div>|<del class=\"diffchange diffchange-inline\">passion</del></div></td>\n  <td class=\"diff-marker\">+</td>\n  <td class=\"diff-addedline\"><div>|<ins class=\"diffchange diffchange-inline\">&lt;center&gt;x&lt;/center&gt;</ins></div></td>\n</tr>\n<tr>\n  <td class=\"diff-marker\">−</td>\n  <td class=\"diff-deletedline\"><div>|<del class=\"diffchange diffchange-inline\">commitment</del></div></td>\n  <td class=\"diff-marker\">+</td>\n  <td class=\"diff-addedline\"><div>|<ins class=\"diffchange diffchange-inline\">&lt;center&gt;x&lt;/center&gt;</ins></div></td>\n</tr>\n<tr>\n  <td class=\"diff-marker\">&#160;</td>\n  <td class=\"diff-context\"><div>|-</div></td>\n  <td class=\"diff-marker\">&#160;</td>\n  <td class=\"diff-context\"><div>|-</div></td>\n</tr>\n<tr>\n  <td class=\"diff-marker\">&#160;</td>\n  <td class=\"diff-context\"><div>|'''Consummate love'''</div></td>\n  <td class=\"diff-marker\">&#160;</td>\n  <td class=\"diff-context\"><div>|'''Consummate love'''</div></td>\n</tr>\n<tr>\n  <td class=\"diff-marker\">−</td>\n  <td class=\"diff-deletedline\"><div>|<del class=\"diffchange diffchange-inline\">intimacy</del></div></td>\n  <td class=\"diff-marker\">+</td>\n  <td class=\"diff-addedline\"><div>|<ins class=\"diffchange diffchange-inline\">&lt;center&gt;x&lt;/center&gt;</ins></div></td>\n</tr>\n<tr>\n  <td class=\"diff-marker\">−</td>\n  <td class=\"diff-deletedline\"><div>|<del class=\"diffchange diffchange-inline\">passion</del></div></td>\n  <td class=\"diff-marker\">+</td>\n  <td class=\"diff-addedline\"><div>|<ins class=\"diffchange diffchange-inline\">&lt;center&gt;x&lt;/center&gt;</ins></div></td>\n</tr>\n<tr>\n  <td class=\"diff-marker\">−</td>\n  <td class=\"diff-deletedline\"><div>|<del class=\"diffchange diffchange-inline\">commitment</del></div></td>\n  <td class=\"diff-marker\">+</td>\n  <td class=\"diff-addedline\"><div>|<ins class=\"diffchange diffchange-inline\">&lt;center&gt;x&lt;/center&gt;</ins></div></td>\n</tr>\n<tr>\n  <td class=\"diff-marker\">&#160;</td>\n  <td class=\"diff-context\"><div>|}</div></td>\n  <td class=\"diff-marker\">&#160;</td>\n  <td class=\"diff-context\"><div>|}</div></td>\n</tr>\n<tr>\n  <td class=\"diff-marker\">&#160;</td>\n  <td class=\"diff-context\"></td>\n  <td class=\"diff-marker\">&#160;</td>\n  <td class=\"diff-context\"></td>\n</tr>\n\n<!-- diff cache key enwiki:diff:version:1.11a:oldid:31614344:newid:31787793 -->\n",
    "from": 31614344
  }
}