{
  "comment": "",
  "timestamp": "2011-02-17T14:31:31Z",
  "revid": 414437741,
  "user": "Dalton2",
  "parentid": 414437195,
  "diff": {
    "to": 414437741,
    "*": "<tr>\n  <td colspan=\"2\" class=\"diff-lineno\">Line 10:</td>\n  <td colspan=\"2\" class=\"diff-lineno\">Line 10:</td>\n</tr>\n<tr>\n  <td class=\"diff-marker\">&#160;</td>\n  <td class=\"diff-context\"></td>\n  <td class=\"diff-marker\">&#160;</td>\n  <td class=\"diff-context\"></td>\n</tr>\n<tr>\n  <td class=\"diff-marker\">&#160;</td>\n  <td class=\"diff-context\"><div>&lt;!-- themes --&gt;Love in its various forms acts as a major facilitator of [[interpersonal relationship]]s and, owing to its central psychological importance, is one of the most common themes in the [[creative arts]].</div></td>\n  <td class=\"diff-marker\">&#160;</td>\n  <td class=\"diff-context\"><div>&lt;!-- themes --&gt;Love in its various forms acts as a major facilitator of [[interpersonal relationship]]s and, owing to its central psychological importance, is one of the most common themes in the [[creative arts]].</div></td>\n</tr>\n<tr>\n  <td colspan=\"2\" class=\"diff-empty\">&#160;</td>\n  <td class=\"diff-marker\">+</td>\n  <td class=\"diff-addedline\"></td>\n</tr>\n<tr>\n  <td colspan=\"2\" class=\"diff-empty\">&#160;</td>\n  <td class=\"diff-marker\">+</td>\n  <td class=\"diff-addedline\"><div>[[Gilles Deleuze]] y [[Félix Guattari]] consider that [[capitalism]] produces a perversion of the natural love concept, by placing the human being as part of a production machine, and thus destructing the concept of body and soul.&lt;ref name=\"Deleuze\"&gt;Gilles Deleuze. Félix Guattari. ''[http://books.google.es/books?id=FQe7w8psqfQC&amp;printsec=frontcover&amp;source=gbs_ge_summary_r&amp;cad=0#v=onepage&amp;q&amp;f=false El anti Edipo]''. 1972, 1985. ISBN 978-84-7509-329-1.&lt;/ref&gt;</div></td>\n</tr>\n<tr>\n  <td class=\"diff-marker\">&#160;</td>\n  <td class=\"diff-context\"></td>\n  <td class=\"diff-marker\">&#160;</td>\n  <td class=\"diff-context\"></td>\n</tr>\n<tr>\n  <td class=\"diff-marker\">&#160;</td>\n  <td class=\"diff-context\"><div>==Definitions==</div></td>\n  <td class=\"diff-marker\">&#160;</td>\n  <td class=\"diff-context\"><div>==Definitions==</div></td>\n</tr>\n\n<!-- diff cache key enwiki:diff:version:1.11a:oldid:414437195:newid:414437741 -->\n",
    "from": 414437195
  }
}