{
  "comment": "/* Scientific models */",
  "timestamp": "2006-03-02T23:35:00Z",
  "revid": 41971529,
  "anon": "",
  "user": "203.17.156.230",
  "parentid": 41959357,
  "diff": {
    "to": 41971529,
    "*": "<tr>\n  <td colspan=\"2\" class=\"diff-lineno\">Line 86:</td>\n  <td colspan=\"2\" class=\"diff-lineno\">Line 86:</td>\n</tr>\n<tr>\n  <td class=\"diff-marker\">&#160;</td>\n  <td class=\"diff-context\"><div>|}</div></td>\n  <td class=\"diff-marker\">&#160;</td>\n  <td class=\"diff-context\"><div>|}</div></td>\n</tr>\n<tr>\n  <td class=\"diff-marker\">&#160;</td>\n  <td class=\"diff-context\"><div>&lt;/center&gt;</div></td>\n  <td class=\"diff-marker\">&#160;</td>\n  <td class=\"diff-context\"><div>&lt;/center&gt;</div></td>\n</tr>\n<tr>\n  <td colspan=\"2\" class=\"diff-empty\">&#160;</td>\n  <td class=\"diff-marker\">+</td>\n  <td class=\"diff-addedline\"></td>\n</tr>\n<tr>\n  <td colspan=\"2\" class=\"diff-empty\">&#160;</td>\n  <td class=\"diff-marker\">+</td>\n  <td class=\"diff-addedline\"></td>\n</tr>\n<tr>\n  <td colspan=\"2\" class=\"diff-empty\">&#160;</td>\n  <td class=\"diff-marker\">+</td>\n  <td class=\"diff-addedline\"></td>\n</tr>\n<tr>\n  <td colspan=\"2\" class=\"diff-empty\">&#160;</td>\n  <td class=\"diff-marker\">+</td>\n  <td class=\"diff-addedline\"><div>Remy Loves Stacey!!!!!!!</div></td>\n</tr>\n<tr>\n  <td colspan=\"2\" class=\"diff-empty\">&#160;</td>\n  <td class=\"diff-marker\">+</td>\n  <td class=\"diff-addedline\"></td>\n</tr>\n<tr>\n  <td colspan=\"2\" class=\"diff-empty\">&#160;</td>\n  <td class=\"diff-marker\">+</td>\n  <td class=\"diff-addedline\"></td>\n</tr>\n<tr>\n  <td class=\"diff-marker\">&#160;</td>\n  <td class=\"diff-context\"></td>\n  <td class=\"diff-marker\">&#160;</td>\n  <td class=\"diff-context\"></td>\n</tr>\n<tr>\n  <td class=\"diff-marker\">&#160;</td>\n  <td class=\"diff-context\"><div>===Formulaic models===</div></td>\n  <td class=\"diff-marker\">&#160;</td>\n  <td class=\"diff-context\"><div>===Formulaic models===</div></td>\n</tr>\n\n<!-- diff cache key enwiki:diff:version:1.11a:oldid:41959357:newid:41971529 -->\n",
    "from": 41959357
  }
}