{
  "comment": "Revert to 67.154.173.222",
  "timestamp": "2006-03-07T03:37:45Z",
  "revid": 42589109,
  "user": "JHMM13",
  "parentid": 42589027,
  "diff": {
    "to": 42589109,
    "*": "<tr>\n  <td colspan=\"2\" class=\"diff-lineno\">Line 10:</td>\n  <td colspan=\"2\" class=\"diff-lineno\">Line 10:</td>\n</tr>\n<tr>\n  <td class=\"diff-marker\">&#160;</td>\n  <td class=\"diff-context\"><div>==Scientific models==</div></td>\n  <td class=\"diff-marker\">&#160;</td>\n  <td class=\"diff-context\"><div>==Scientific models==</div></td>\n</tr>\n<tr>\n  <td class=\"diff-marker\">&#160;</td>\n  <td class=\"diff-context\"></td>\n  <td class=\"diff-marker\">&#160;</td>\n  <td class=\"diff-context\"></td>\n</tr>\n<tr>\n  <td class=\"diff-marker\">−</td>\n  <td class=\"diff-deletedline\"><div>== Headline text ==</div></td>\n  <td colspan=\"2\" class=\"diff-empty\">&#160;</td>\n</tr>\n<tr>\n  <td class=\"diff-marker\">−</td>\n  <td class=\"diff-deletedline\"><div>Mindy Loves Anthony Forever!</div></td>\n  <td colspan=\"2\" class=\"diff-empty\">&#160;</td>\n</tr>\n<tr>\n  <td class=\"diff-marker\">&#160;</td>\n  <td class=\"diff-context\"><div>Throughout history, predominately, [[philosophy]] and [[religion]] have speculated the most into the phenomena of love.  In the last century, the science of [[psychology]] has written a great deal on the subject.  Recently, however, the sciences of [[evolutionary psychology]], [[evolutionary biology]], [[anthropology]], [[neuroscience]], and [[biology]] have begun to take center stage in discussion as to the nature and function of love.</div></td>\n  <td class=\"diff-marker\">&#160;</td>\n  <td class=\"diff-context\"><div>Throughout history, predominately, [[philosophy]] and [[religion]] have speculated the most into the phenomena of love.  In the last century, the science of [[psychology]] has written a great deal on the subject.  Recently, however, the sciences of [[evolutionary psychology]], [[evolutionary biology]], [[anthropology]], [[neuroscience]], and [[biology]] have begun to take center stage in discussion as to the nature and function of love.</div></td>\n</tr>\n<tr>\n  <td class=\"diff-marker\">&#160;</td>\n  <td class=\"diff-context\"></td>\n  <td class=\"diff-marker\">&#160;</td>\n  <td class=\"diff-context\"></td>\n</tr>\n\n<!-- diff cache key enwiki:diff:version:1.11a:oldid:42589027:newid:42589109 -->\n",
    "from": 42589027
  },
  "minor": ""
}