{
  "comment": "/* Political views */",
  "timestamp": "2012-06-13T01:17:06Z",
  "revid": 497321514,
  "user": "Eduen",
  "parentid": 497321421,
  "diff": {
    "to": 497321514,
    "*": "<tr>\n  <td colspan=\"2\" class=\"diff-lineno\">Line 220:</td>\n  <td colspan=\"2\" class=\"diff-lineno\">Line 220:</td>\n</tr>\n<tr>\n  <td class=\"diff-marker\">&#160;</td>\n  <td class=\"diff-context\"></td>\n  <td class=\"diff-marker\">&#160;</td>\n  <td class=\"diff-context\"></td>\n</tr>\n<tr>\n  <td class=\"diff-marker\">&#160;</td>\n  <td class=\"diff-context\"><div>== Political views ==</div></td>\n  <td class=\"diff-marker\">&#160;</td>\n  <td class=\"diff-context\"><div>== Political views ==</div></td>\n</tr>\n<tr>\n  <td colspan=\"2\" class=\"diff-empty\">&#160;</td>\n  <td class=\"diff-marker\">+</td>\n  <td class=\"diff-addedline\"><div>=== Free love ===</div></td>\n</tr>\n<tr>\n  <td class=\"diff-marker\">&#160;</td>\n  <td class=\"diff-context\"><div>{{Main|Free love}}</div></td>\n  <td class=\"diff-marker\">&#160;</td>\n  <td class=\"diff-context\"><div>{{Main|Free love}}</div></td>\n</tr>\n<tr>\n  <td class=\"diff-marker\">&#160;</td>\n  <td class=\"diff-context\"><div>The term '''free love''' has been used &lt;ref&gt;[http://library.syr.edu/digital/collections/h/Hand-bookOfTheOneidaCommunity/ The Handbook] of the [[Oneida Community]] claims to have coined the term around 1850, and laments that its use was appropriated by [[socialist]]s to attack marriage, an institution that they felt protected women and children from abandonment&lt;/ref&gt; to describe a [[social movement]] that rejects [[marriage]], which is seen as a form of social bondage. The Free Love movement’s initial goal was to separate the state from sexual matters such as marriage, [[birth control]], and [[adultery]]. It claimed that such issues were the concern of the people involved, and no one else.&lt;ref&gt;McElroy, Wendy. \"The Free Love Movement and Radical Individualism.\" Libertarian Enterprise .19 (1996): 1.&lt;/ref&gt;</div></td>\n  <td class=\"diff-marker\">&#160;</td>\n  <td class=\"diff-context\"><div>The term '''free love''' has been used &lt;ref&gt;[http://library.syr.edu/digital/collections/h/Hand-bookOfTheOneidaCommunity/ The Handbook] of the [[Oneida Community]] claims to have coined the term around 1850, and laments that its use was appropriated by [[socialist]]s to attack marriage, an institution that they felt protected women and children from abandonment&lt;/ref&gt; to describe a [[social movement]] that rejects [[marriage]], which is seen as a form of social bondage. The Free Love movement’s initial goal was to separate the state from sexual matters such as marriage, [[birth control]], and [[adultery]]. It claimed that such issues were the concern of the people involved, and no one else.&lt;ref&gt;McElroy, Wendy. \"The Free Love Movement and Radical Individualism.\" Libertarian Enterprise .19 (1996): 1.&lt;/ref&gt;</div></td>\n</tr>\n",
    "from": 497321421
  }
}