{
  "comment": "+interwiki",
  "timestamp": "2007-01-22T00:23:46Z",
  "revid": 102324602,
  "user": "Numbo3",
  "parentid": 102065330,
  "diff": {
    "to": 102324602,
    "*": "<tr>\n  <td colspan=\"2\" class=\"diff-lineno\">Line 207:</td>\n  <td colspan=\"2\" class=\"diff-lineno\">Line 207:</td>\n</tr>\n<tr>\n  <td class=\"diff-marker\">&#160;</td>\n  <td class=\"diff-context\"></td>\n  <td class=\"diff-marker\">&#160;</td>\n  <td class=\"diff-context\"></td>\n</tr>\n<tr>\n  <td class=\"diff-marker\">&#160;</td>\n  <td class=\"diff-context\"><div>[[ar:أخلاق]]</div></td>\n  <td class=\"diff-marker\">&#160;</td>\n  <td class=\"diff-context\"><div>[[ar:أخلاق]]</div></td>\n</tr>\n<tr>\n  <td colspan=\"2\" class=\"diff-empty\">&#160;</td>\n  <td class=\"diff-marker\">+</td>\n  <td class=\"diff-addedline\"><div>[[bar:Ethik]]</div></td>\n</tr>\n<tr>\n  <td class=\"diff-marker\">&#160;</td>\n  <td class=\"diff-context\"><div>[[bs:Etika]]</div></td>\n  <td class=\"diff-marker\">&#160;</td>\n  <td class=\"diff-context\"><div>[[bs:Etika]]</div></td>\n</tr>\n<tr>\n  <td class=\"diff-marker\">&#160;</td>\n  <td class=\"diff-context\"><div>[[bg:Етика]]</div></td>\n  <td class=\"diff-marker\">&#160;</td>\n  <td class=\"diff-context\"><div>[[bg:Етика]]</div></td>\n</tr>\n<tr>\n  <td colspan=\"2\" class=\"diff-lineno\">Line 222:</td>\n  <td colspan=\"2\" class=\"diff-lineno\">Line 223:</td>\n</tr>\n<tr>\n  <td class=\"diff-marker\">&#160;</td>\n  <td class=\"diff-context\"><div>[[hy:Էթիկա]]</div></td>\n  <td class=\"diff-marker\">&#160;</td>\n  <td class=\"diff-context\"><div>[[hy:Էթիկա]]</div></td>\n</tr>\n<tr>\n  <td class=\"diff-marker\">&#160;</td>\n  <td class=\"diff-context\"><div>[[hr:Etika]]</div></td>\n  <td class=\"diff-marker\">&#160;</td>\n  <td class=\"diff-context\"><div>[[hr:Etika]]</div></td>\n</tr>\n<tr>\n  <td class=\"diff-marker\">−</td>\n  <td class=\"diff-deletedline\"><div>[[ia:Ethica]]</div></td>\n  <td colspan=\"2\" class=\"diff-empty\">&#160;</td>\n</tr>\n<tr>\n  <td class=\"diff-marker\">&#160;</td>\n  <td class=\"diff-context\"><div>[[id:Etika]]</div></td>\n  <td class=\"diff-marker\">&#160;</td>\n  <td class=\"diff-context\"><div>[[id:Etika]]</div></td>\n</tr>\n<tr>\n  <td colspan=\"2\" class=\"diff-empty\">&#160;</td>\n  <td class=\"diff-marker\">+</td>\n  <td class=\"diff-addedline\"><div>[[ia:Ethica]]</div></td>\n</tr>\n<tr>\n  <td class=\"diff-marker\">&#160;</td>\n  <td class=\"diff-context\"><div>[[is:Siðfræði]]</div></td>\n  <td class=\"diff-marker\">&#160;</td>\n  <td class=\"diff-context\"><div>[[is:Siðfræði]]</div></td>\n</tr>\n<tr>\n  <td class=\"diff-marker\">&#160;</td>\n  <td class=\"diff-context\"><div>[[it:Etica]]</div></td>\n  <td class=\"diff-marker\">&#160;</td>\n  <td class=\"diff-context\"><div>[[it:Etica]]</div></td>\n</tr>\n\n<!-- diff cache key enwiki:diff:version:1.11a:oldid:102065330:newid:102324602 -->\n",
    "from": 102065330
  },
  "minor": ""
}