{
  "comment": "/* See also */ fixing link",
  "timestamp": "2007-11-07T23:57:41Z",
  "revid": 169988593,
  "user": "Anarchia",
  "parentid": 169522129,
  "diff": {
    "to": 169988593,
    "*": "<tr>\n  <td colspan=\"2\" class=\"diff-lineno\">Line 90:</td>\n  <td colspan=\"2\" class=\"diff-lineno\">Line 90:</td>\n</tr>\n<tr>\n  <td class=\"diff-marker\">&#160;</td>\n  <td class=\"diff-context\"><div>* [[Moral nihilism]]</div></td>\n  <td class=\"diff-marker\">&#160;</td>\n  <td class=\"diff-context\"><div>* [[Moral nihilism]]</div></td>\n</tr>\n<tr>\n  <td class=\"diff-marker\">&#160;</td>\n  <td class=\"diff-context\"><div>* [[Ethical skepticism]]</div></td>\n  <td class=\"diff-marker\">&#160;</td>\n  <td class=\"diff-context\"><div>* [[Ethical skepticism]]</div></td>\n</tr>\n<tr>\n  <td class=\"diff-marker\">−</td>\n  <td class=\"diff-deletedline\"><div>* [[Altruism (<del class=\"diffchange diffchange-inline\">ethical doctrine</del>)]]</div></td>\n  <td class=\"diff-marker\">+</td>\n  <td class=\"diff-addedline\"><div>* [[Altruism (<ins class=\"diffchange diffchange-inline\">ethics</ins>)]]</div></td>\n</tr>\n<tr>\n  <td class=\"diff-marker\">&#160;</td>\n  <td class=\"diff-context\"><div>* [[Ethical egoism]]</div></td>\n  <td class=\"diff-marker\">&#160;</td>\n  <td class=\"diff-context\"><div>* [[Ethical egoism]]</div></td>\n</tr>\n<tr>\n  <td class=\"diff-marker\">&#160;</td>\n  <td class=\"diff-context\"><div>* [[Bioethics]]</div></td>\n  <td class=\"diff-marker\">&#160;</td>\n  <td class=\"diff-context\"><div>* [[Bioethics]]</div></td>\n</tr>\n\n<!-- diff cache key enwiki:diff:version:1.11a:oldid:169522129:newid:169988593 -->\n",
    "from": 169522129
  },
  "minor": ""
}